ignorely/main.py
ignorely/utils.py
ignorely/commands/copy_files.py
ignorely/commands/export_files.py
ignorely/commands/init.py
ignorely/commands/ls_files.py
ignorely-3.0.0.dist-info/licenses/LICENSE
ignorely-3.0.0.dist-info/METADATA
ignorely-3.0.0.dist-info/WHEEL
ignorely-3.0.0.dist-info/entry_points.txt
ignorely-3.0.0.dist-info/top_level.txt
ignorely-3.0.0.dist-info/RECORD
