Metadata-Version: 2.4
Name: ignorely
Version: 3.0.0
Summary: CLI tool for Git-style file filtering and copying with include/exclude pattern management
Author-email: Sisung Kim <sisung.kim1@gmail.com>
Requires-Python: <4.0,>=3.10
License-File: LICENSE
Requires-Dist: cleo<3.0.0,>=2.1.0
Requires-Dist: pathspec<0.13.0,>=0.12.1
Dynamic: license-file
